brainfm/__init__.py
brainfm/main/__init__.py
brainfm/main/cli.py
brainfm-3.0.0.dist-info/LICENSE
brainfm-3.0.0.dist-info/METADATA
brainfm-3.0.0.dist-info/WHEEL
brainfm-3.0.0.dist-info/entry_points.txt
brainfm-3.0.0.dist-info/top_level.txt
brainfm-3.0.0.dist-info/RECORD
