Metadata-Version: 2.1
Name: brainfm
Version: 3.0.0
Summary: Unofficial python API for brain.fm
Home-page: https://github.com/numberoverzero/brainfm
Author: Joe Cross
Author-email: joe.mcross@gmail.com
License: MIT
Keywords: brainfm api
Platform: any
Classifier: Development Status :: 2 - Pre-Alpha
Classifier: Intended Audience :: Developers
Classifier: License :: OSI Approved :: MIT License
Classifier: Operating System :: OS Independent
Classifier: Programming Language :: Python
Classifier: Programming Language :: Python :: 3
Classifier: Programming Language :: Python :: 3.5
Classifier: Topic :: Software Development :: Libraries
Requires-Dist: click (>=6)
Requires-Dist: jmespath (>=0.9)
Requires-Dist: requests (>=2.11)
Requires-Dist: terminaltables (>=3.1)
